stylefact/__init__.py
stylefact/_version.py
stylefact/finance.py
stylefact/utils.py
stylefact/visualize.py
stylefact-0.0.1.dist-info/METADATA
stylefact-0.0.1.dist-info/RECORD
stylefact-0.0.1.dist-info/WHEEL
stylefact-0.0.1.dist-info/top_level.txt
